<MeshPointDevice time="580" address="00:00:00:00:00:06">
<Statistics
txUnicastData="0"
txUnicastDataBytes="0"
txBroadcastData="0"
txBroadcastDataBytes="0"
rxUnicastData="0"
rxUnicastDataBytes="0"
rxBroadcastData="13"
rxBroadcastDataBytes="364"
fwdUnicastData="4762"
fwdUnicastDataBytes="894616"
fwdBroadcastData="13"
fwdBroadcastDataBytes="364"
/>
<Interface BeaconInterval="0.5" Channel="0" SumOfNode="12626213071" Address = "00:00:00:00:00:06">
<Statistics rxBeacons="4559" txFrames="8350" txBytes="1092648" rxFrames="8763" rxBytes="1117823"/>
</Interface>
<Hwmp address="00:00:00:00:00:06"
maxQueueSize="255"
Dot11MeshHWMPmaxPREQretries="3"
Dot11MeshHWMPnetDiameterTraversalTime="0.1024"
Dot11MeshHWMPpreqMinInterval="0.1024"
Dot11MeshHWMPperrMinInterval="0.1024"
Dot11MeshHWMPactiveRootTimeout="5.12"
Dot11MeshHWMPactivePathTimeout="5.12"
Dot11MeshHWMPpathToRootInterval="2.048"
Dot11MeshHWMPrannInterval="5.12"
isRoot="0"
maxTtl="32"
unicastPerrThreshold="32"
unicastPreqThreshold="1"
unicastDataThreshold="1"
doFlag="0"
rfFlag="1">
<Statistics txUnicast="4762" txBroadcast="13" txBytes="933076" droppedTtl="0" totalQueued="0" totalDropped="28" initiatedPreq="0" initiatedPrep="581" initiatedPerr="130"/>
<HwmpProtocolMac
address ="00:00:00:00:00:06">
<Statistics txPreq= "661"
txPrep="2348"
txPerr="210"
rxPreq="1654"
rxPrep="1777"
rxPerr="123"
txMgt="3219"
txMgtBytes="116392"
rxMgt="3554"
rxMgtBytes="134078"
txData="4775"
txDataBytes="933180"
rxData="4823"
rxDataBytes="939388"/>
</HwmpProtocolMac>
</Hwmp>
<PeerManagementProtocol>
<Statistics linksTotal="4" linksOpened="85" linksClosed="81"/>
<PeerManagementProtocolMac address="00:00:00:00:00:06">
<Statistics txOpen="134"
txConfirm="85"
txClose="153"
rxOpen="108"
rxConfirm="85"
rxClose="153"
dropped="16"
brokenMgt="0"
txMgt="372"
txMgtBytes="15022"
rxMgt="346"
rxMgtBytes="12926"
beaconShift="59"/>
</PeerManagementProtocolMac>
<PeerLink
localAddress="00:00:00:00:00:06"
peerInterfaceAddress="00:00:00:00:00:02"
peerMeshPointAddress="00:00:00:00:00:02"
metric="151"
lastBeacon="579.534"
localLinkId="122"
peerLinkId="36"
assocId="121"
/>
<PeerLink
localAddress="00:00:00:00:00:06"
peerInterfaceAddress="00:00:00:00:00:0a"
peerMeshPointAddress="00:00:00:00:00:0a"
metric="150"
lastBeacon="579.947"
localLinkId="128"
peerLinkId="122"
assocId="127"
/>
<PeerLink
localAddress="00:00:00:00:00:06"
peerInterfaceAddress="00:00:00:00:00:05"
peerMeshPointAddress="00:00:00:00:00:05"
metric="162"
lastBeacon="579.58"
localLinkId="130"
peerLinkId="59"
assocId="129"
/>
<PeerLink
localAddress="00:00:00:00:00:06"
peerInterfaceAddress="00:00:00:00:00:07"
peerMeshPointAddress="00:00:00:00:00:07"
metric="451"
lastBeacon="579.995"
localLinkId="134"
peerLinkId="109"
assocId="133"
/>
</PeerManagementProtocol>
</MeshPointDevice>
